loit/__init__.py
loit/loit.py
loit-0.0.2.1.dist-info/LICENSE
loit-0.0.2.1.dist-info/METADATA
loit-0.0.2.1.dist-info/WHEEL
loit-0.0.2.1.dist-info/top_level.txt
loit-0.0.2.1.dist-info/RECORD
