Metadata-Version: 2.1
Name: loit
Version: 0.0.2.1
Summary: Lot Of Indic Tweets
Home-page: https://github.com/bedapudi6788/LOIT
Author: BEDAPUDI PRANEETH
Author-email: praneeth@bpraneeth.com
License: GPLv3
Platform: UNKNOWN
Classifier: License :: OSI Approved :: GNU General Public License v3 (GPLv3)
Classifier: Programming Language :: Python
Classifier: Programming Language :: Python :: 3
Classifier: Programming Language :: Python :: 3.6
Classifier: Programming Language :: Python :: Implementation :: CPython
Classifier: Programming Language :: Python :: Implementation :: PyPy
Requires-Python: >=3.5.0
Requires-Dist: pydload
Requires-Dist: progressbar2
